musicgen/__init__.py
musicgen/api.py
musicgen/batch.py
musicgen/cli.py
musicgen/generator.py
musicgen/py.typed
musicgen_minimal-1.1.2.dist-info/licenses/LICENSE
musicgen_minimal-1.1.2.dist-info/METADATA
musicgen_minimal-1.1.2.dist-info/WHEEL
musicgen_minimal-1.1.2.dist-info/entry_points.txt
musicgen_minimal-1.1.2.dist-info/top_level.txt
musicgen_minimal-1.1.2.dist-info/RECORD
