Metadata-Version: 2.4
Name: musicgen-minimal
Version: 1.1.2
Summary: Simple text-to-music generation that actually works - no enterprise complexity
Author-email: MusicGen Minimal Team <hello@musicgen-minimal.dev>
License-Expression: MIT
Project-URL: Homepage, https://github.com/musicgen-minimal/musicgen-minimal
Project-URL: Repository, https://github.com/musicgen-minimal/musicgen-minimal
Project-URL: Issues, https://github.com/musicgen-minimal/musicgen-minimal/issues
Project-URL: Documentation, https://github.com/musicgen-minimal/musicgen-minimal#readme
Project-URL: Changelog, https://github.com/musicgen-minimal/musicgen-minimal/releases
Keywords: music,generation,ai,text-to-music,musicgen,audio,transformers
Classifier: Development Status :: 5 - Production/Stable
Classifier: Intended Audience :: Developers
Classifier: Intended Audience :: Science/Research
Classifier: Operating System :: OS Independent
Classifier: Programming Language :: Python :: 3
Classifier: Programming Language :: Python :: 3.8
Classifier: Programming Language :: Python :: 3.9
Classifier: Programming Language :: Python :: 3.10
Classifier: Programming Language :: Python :: 3.11
Classifier: Programming Language :: Python :: 3.12
Classifier: Topic :: Multimedia :: Sound/Audio
Classifier: Topic :: Multimedia :: Sound/Audio :: Analysis
Classifier: Topic :: Scientific/Engineering :: Artificial Intelligence
Classifier: Topic :: Software Development :: Libraries :: Python Modules
Requires-Python: >=3.8
License-File: LICENSE
Requires-Dist: torch>=2.0.0
Requires-Dist: transformers>=4.35.0
Requires-Dist: soundfile>=0.12.0
Requires-Dist: numpy>=1.21.0
Requires-Dist: typer>=0.9.0
Requires-Dist: rich>=13.0.0
Requires-Dist: requests>=2.25.0
Requires-Dist: pandas>=1.5.0
Provides-Extra: audio
Requires-Dist: pydub>=0.25.0; extra == "audio"
Provides-Extra: api
Requires-Dist: fastapi>=0.100.0; extra == "api"
Requires-Dist: uvicorn[standard]>=0.23.0; extra == "api"
Requires-Dist: pydantic>=2.0.0; extra == "api"
Provides-Extra: dev
Requires-Dist: pytest>=7.0.0; extra == "dev"
Requires-Dist: pytest-cov>=4.0.0; extra == "dev"
Requires-Dist: black>=23.0.0; extra == "dev"
Requires-Dist: isort>=5.12.0; extra == "dev"
Requires-Dist: flake8>=6.0.0; extra == "dev"
Requires-Dist: mypy>=1.0.0; extra == "dev"
Provides-Extra: all
Requires-Dist: musicgen-minimal[api,audio,dev]; extra == "all"
Dynamic: license-file
